t_toolbox/__init__.py
t_toolbox/freeform/__init__.py
t_toolbox-0.1.2.dist-info/LICENSE
t_toolbox-0.1.2.dist-info/METADATA
t_toolbox-0.1.2.dist-info/WHEEL
t_toolbox-0.1.2.dist-info/RECORD
