Metadata-Version: 2.1
Name: t-toolbox
Version: 0.1.2
Summary: 
License: GPL-3.0-or-later
Author: taitep
Author-email: taitep@taitep.se
Requires-Python: >=3.8,<4.0
Classifier: License :: OSI Approved :: GNU General Public License v3 or later (GPLv3+)
Classifier: Programming Language :: Python :: 3
Classifier: Programming Language :: Python :: 3.8
Classifier: Programming Language :: Python :: 3.9
Classifier: Programming Language :: Python :: 3.10
Classifier: Programming Language :: Python :: 3.11
Classifier: Programming Language :: Python :: 3.12
Classifier: Programming Language :: Python :: 3.13
Requires-Dist: consumable (>=1.1.3,<2.0.0)
